jupyterlab_omnisci/__init__.py
jupyterlab_omnisci/altair.py
jupyterlab_omnisci/magics.py
jupyterlab_omnisci/serverextension/__init__.py
jupyterlab_omnisci/serverextension/config.py
jupyterlab_omnisci/serverextension/handlers.py
jupyterlab_omnisci/serverextension/session.py
jupyterlab_omnisci-3.0.0.dist-info/LICENSE
jupyterlab_omnisci-3.0.0.dist-info/METADATA
jupyterlab_omnisci-3.0.0.dist-info/WHEEL
jupyterlab_omnisci-3.0.0.dist-info/top_level.txt
jupyterlab_omnisci-3.0.0.dist-info/RECORD
