Metadata-Version: 2.1
Name: jupyterlab-omnisci
Version: 3.0.0
Summary: Omnisci integration with JupyterLab
Home-page: https://github.com/omnisci/jupyterlab-omnisci
License: UNKNOWN
Platform: UNKNOWN
Requires-Dist: ipywidgets
Requires-Dist: jupyterlab (<3.0.0,>=2.0.0)
Requires-Dist: pymapd (>=0.12.0)
Requires-Dist: pyyaml
Requires-Dist: vdom
Requires-Dist: tornado
Requires-Dist: altair
Requires-Dist: ibis-framework
Provides-Extra: dev
Requires-Dist: jupyter-book ; extra == 'dev'
Requires-Dist: black ; extra == 'dev'
Requires-Dist: wheel ; extra == 'dev'
Requires-Dist: twine ; extra == 'dev'
